napalm_h3c_comware/__init__.py
napalm_h3c_comware/comware.py
napalm_h3c_comware/utils/__init__.py
napalm_h3c_comware/utils/helpers.py
napalm_h3c_comware/utils/textfsm_templates/display_arp.tpl
napalm_h3c_comware/utils/textfsm_templates/display_cpu-usage_summary.tpl
napalm_h3c_comware/utils/textfsm_templates/display_current-configuration_configuration_irf-port.tpl
napalm_h3c_comware/utils/textfsm_templates/display_device_manuinfo.tpl
napalm_h3c_comware/utils/textfsm_templates/display_environment.tpl
napalm_h3c_comware/utils/textfsm_templates/display_fan.tpl
napalm_h3c_comware/utils/textfsm_templates/display_interface.tpl
napalm_h3c_comware/utils/textfsm_templates/display_ip_interface.tpl
napalm_h3c_comware/utils/textfsm_templates/display_lldp_neighbor-information_verbose.tpl
napalm_h3c_comware/utils/textfsm_templates/display_mac-address.tpl
napalm_h3c_comware/utils/textfsm_templates/display_mac-address_mac-move.tpl
napalm_h3c_comware/utils/textfsm_templates/display_memory.tpl
napalm_h3c_comware/utils/textfsm_templates/display_power.tpl
napalm_h3c_comware/utils/textfsm_templates/display_version.tpl
napalm_h3c_comware/utils/textfsm_templates/display_vlan_all.tpl
napalm_h3c_comware-0.1.5.dist-info/AUTHORS
napalm_h3c_comware-0.1.5.dist-info/LICENSE
napalm_h3c_comware-0.1.5.dist-info/METADATA
napalm_h3c_comware-0.1.5.dist-info/WHEEL
napalm_h3c_comware-0.1.5.dist-info/top_level.txt
napalm_h3c_comware-0.1.5.dist-info/RECORD
