Metadata-Version: 2.1
Name: napalm-h3c-comware
Version: 0.1.5
Summary: NAPALM driver for H3C Comware V7 network devices, over ssh.
Home-page: https://github.com/napalm-automation-community/napalm-h3c-cw7-ssh/
Author: Eric Wu
Author-email: vip@xdai.vip
License: Apache 2.0
Project-URL: Bug Tracker, https://github.com/napalm-automation-community/napalm-h3c-cw7-ssh/issues
Classifier: Topic :: Utilities
Classifier: License :: OSI Approved :: Apache Software License
Classifier: Development Status :: 4 - Beta
Classifier: Programming Language :: Python
Classifier: Programming Language :: Python :: 3
Classifier: Programming Language :: Python :: 3.6
Classifier: Programming Language :: Python :: 3.7
Classifier: Programming Language :: Python :: 3.8
Classifier: Operating System :: POSIX :: Linux
Classifier: Operating System :: MacOS
License-File: LICENSE
License-File: AUTHORS
Requires-Dist: napalm (>=3.0.0)
